rest_framework_tracking/__init__.py
rest_framework_tracking/admin.py
rest_framework_tracking/app_settings.py
rest_framework_tracking/apps.py
rest_framework_tracking/base_mixins.py
rest_framework_tracking/base_models.py
rest_framework_tracking/managers.py
rest_framework_tracking/mixins.py
rest_framework_tracking/models.py
rest_framework_tracking/management/commands/clearapilogs.py
rest_framework_tracking/migrations/0001_initial.py
rest_framework_tracking/migrations/0002_auto_20170118_1713.py
rest_framework_tracking/migrations/0003_add_errors.py
rest_framework_tracking/migrations/0004_add_verbose_name.py
rest_framework_tracking/migrations/0005_auto_20171219_1537.py
rest_framework_tracking/migrations/0006_auto_20180315_1442.py
rest_framework_tracking/migrations/0006_view_and_view_method_nullable.py
rest_framework_tracking/migrations/0007_merge_20180419_1646.py
rest_framework_tracking/migrations/0008_auto_20200201_2048.py
rest_framework_tracking/migrations/0009_view_method_max_length_200.py
rest_framework_tracking/migrations/0010_auto_20200609_1404.py
rest_framework_tracking/migrations/0011_auto_20201117_2016.py
rest_framework_tracking/migrations/__init__.py
rest_framework_tracking/templates/admin/rest_framework_tracking/apirequestlog/change_list.html
drf_api_tracking-1.8.0.dist-info/LICENSE
drf_api_tracking-1.8.0.dist-info/METADATA
drf_api_tracking-1.8.0.dist-info/WHEEL
drf_api_tracking-1.8.0.dist-info/top_level.txt
drf_api_tracking-1.8.0.dist-info/RECORD
